Metadata-Version: 1.0
Name: uwallet
Version: 1.0.0a1
Summary: Python Blockchain Wallet Library
Home-page: https://www.wizardsofindustry.net
Author: Cochise Ruhulessin
Author-email: cochiseruhulessin@gmail.com
License: UNKNOWN
Platform: UNKNOWN
